wavebox/__init__.py
wavebox/components/__init__.py
wavebox/components/controllers.py
wavebox/components/exceptions.py
wavebox/components/middlewares.py
wavebox/components/routes.py
wavebox/components/services.py
wavebox/definitions/__init__.py
wavebox/definitions/applications.py
wavebox/utilities/__init__.py
wavebox/utilities/modifiers.py
wavebox-1.0.1.dist-info/LICENSE
wavebox-1.0.1.dist-info/METADATA
wavebox-1.0.1.dist-info/WHEEL
wavebox-1.0.1.dist-info/top_level.txt
wavebox-1.0.1.dist-info/RECORD
