Metadata-Version: 2.1
Name: wavebox
Version: 1.0.1
Summary: A compact, fast, and easy to use flask backend wrapper
Author-email: Nightsilver Tech <hyperspace018@gmail.com>
Project-URL: Homepage, https://github.com/xoxoist/dicksy
Project-URL: Repository, https://github.com/xoxoist/dicksy
Project-URL: Bug Tracker, https://github.com/xoxoist/dicksy/issues
Keywords: backend,performance,error handling,wrapper,development
Classifier: Programming Language :: Python :: 3.10
Classifier: License :: OSI Approved :: GNU General Public License v3 or later (GPLv3+)
Classifier: Operating System :: OS Independent
Classifier: Intended Audience :: Developers
Classifier: Development Status :: 5 - Production/Stable
Requires-Python: >=3.10
License-File: LICENSE
